__init__.py
sql_data/__init__.py
sql_data/date_formatting.py
sql_data/mysql_operate.py
sql_data-0.1.5.dist-info/LICENSE
sql_data-0.1.5.dist-info/METADATA
sql_data-0.1.5.dist-info/WHEEL
sql_data-0.1.5.dist-info/top_level.txt
sql_data-0.1.5.dist-info/RECORD
