Metadata-Version: 2.1
Name: sql-data
Version: 0.1.5
Summary: Used for SQL data queries.
Author-email: cwj <17800372351@163.com>
License: MIT License        
Keywords: sql,mysql
License-File: LICENSE
